text_histogram.py
text_histogram-0.0.7.dist-info/DESCRIPTION.rst
text_histogram-0.0.7.dist-info/METADATA
text_histogram-0.0.7.dist-info/metadata.json
text_histogram-0.0.7.dist-info/RECORD
text_histogram-0.0.7.dist-info/top_level.txt
text_histogram-0.0.7.dist-info/WHEEL
text_histogram-0.0.7.dist-info/zip-safe
