Metadata-Version: 2.0
Name: text-histogram
Version: 0.0.7
Summary: A dependency-free library to quickly make ascii histograms from data.
Home-page: https://github.com/Kobold/text_histogram
Author: Andy Kish, Jehiah Czebotar
Author-email: agkish@gmail.com
License: Apache License, Version 2.0
Platform: UNKNOWN
Classifier: Programming Language :: Python :: 2
Classifier: Development Status :: 4 - Beta
Classifier: Environment :: Console
Classifier: Intended Audience :: Developers
Classifier: Topic :: Terminals
